html_reporter/__init__.py
html_reporter/redirector.py
html_reporter/result.py
html_reporter/runner.py
html_reporter/status.py
html_reporter/templates/report_template.html
html_reporter-0.2.6.dist-info/AUTHORS.rst
html_reporter-0.2.6.dist-info/LICENSE
html_reporter-0.2.6.dist-info/METADATA
html_reporter-0.2.6.dist-info/WHEEL
html_reporter-0.2.6.dist-info/top_level.txt
html_reporter-0.2.6.dist-info/RECORD
