Metadata-Version: 2.1
Name: html-reporter
Version: 0.2.6
Summary: A TestRunner for use with the Python unittest framework, which generates report in nice HTML files.
Home-page: https://github.com/phongnt570/html-reporter
Author: Tuan-Phong Nguyen
Author-email: tuanphong94@gmail.com
License: MIT license
Keywords: html_reporter,unittest,testrunner,html-reporter,html-test-runner,htmltestrunner
Classifier: Development Status :: 2 - Pre-Alpha
Classifier: Intended Audience :: Developers
Classifier: License :: OSI Approved :: MIT License
Classifier: Natural Language :: English
Classifier: Programming Language :: Python :: 3
Classifier: Programming Language :: Python :: 3.7
Classifier: Programming Language :: Python :: 3.8
Classifier: Programming Language :: Python :: 3.9
Classifier: Programming Language :: Python :: 3.10
Requires-Python: >=3.7
License-File: LICENSE
License-File: AUTHORS.rst
Requires-Dist: Jinja2
